napari_tomotwin/__init__.py
napari_tomotwin/_version.py
napari_tomotwin/anchor_tool.py
napari_tomotwin/cluster_widget.py
napari_tomotwin/load_umap.py
napari_tomotwin/load_umap_widget.py
napari_tomotwin/make_targets.py
napari_tomotwin/napari.yaml
napari_tomotwin/target_manager.py
napari_tomotwin/umap_refiner.py
napari_tomotwin/_qt/__init__.py
napari_tomotwin/_qt/labeled_progress_bar.py
napari_tomotwin/_tests/__init__.py
napari_tomotwin/_tests/test_load_umap.py
napari_tomotwin/_tests/test_make_targets.py
napari_tomotwin-0.4.1.dist-info/LICENSE
napari_tomotwin-0.4.1.dist-info/METADATA
napari_tomotwin-0.4.1.dist-info/WHEEL
napari_tomotwin-0.4.1.dist-info/entry_points.txt
napari_tomotwin-0.4.1.dist-info/top_level.txt
napari_tomotwin-0.4.1.dist-info/RECORD
